{
    "events": [
        {
            "id": 0,
            "name": "移動：礼拝堂",
            "pages": [
                {
                    "id": 0,
                    "list": [
                        {
                            "code": 140,
                            "codeStr": "Sound",
                            "stringArgs": [
                                "SE/door_wood_close_jiten.ogg"
                            ],
                            "intArgs": [
                                33554464,
                                30,
                                0,
                                0,
                                100,
                                100
                            ],
                            "index": 0
                        },
                        {
                            "code": 150,
                            "codeStr": "Picture",
                            "intArgs": [
                                2,
                                4294967286,
                                0,
                                20
                            ],
                            "index": 1
                        },
                        {
                            "code": 300,
                            "codeStr": "CommonEventByName",
                            "stringArgs": [
                                "場所移動"
                            ],
                            "intArgs": [
                                0,
                                52,
                                49,
                                25,
                                9,
                                2,
                                3000000,
                                3000000,
                                3000000
                            ],
                            "index": 2
                        }
                    ]
                },
                {
                    "id": 1,
                    "list": [
                        {
                            "code": 300,
                            "codeStr": "CommonEventByName",
                            "stringArgs": [
                                "吹き出し表示",
                                "Сперва мне нужно положить тарелку..."
                            ],
                            "intArgs": [
                                0,
                                4115,
                                4294967294,
                                0,
                                0,
                                0
                            ],
                            "index": 0
                        },
                        {
                            "code": 201,
                            "codeStr": "Move",
                            "intArgs": [
                                4294967294
                            ],
                            "index": 1
                        }
                    ]
                }
            ]
        },
        {
            "id": 1,
            "name": "移動：厨房",
            "pages": [
                {
                    "id": 0,
                    "list": [
                        {
                            "code": 124,
                            "codeStr": "SetVariableEx",
                            "intArgs": [
                                1100001,
                                4096,
                                4294967294,
                                0
                            ],
                            "index": 0
                        },
                        {
                            "code": 150,
                            "codeStr": "Picture",
                            "intArgs": [
                                2,
                                4294967286,
                                0,
                                20
                            ],
                            "index": 1
                        },
                        {
                            "code": 180,
                            "codeStr": "Wait",
                            "intArgs": [
                                10
                            ],
                            "index": 2
                        },
                        {
                            "code": 111,
                            "codeStr": "VariableCondition",
                            "intArgs": [
                                3,
                                1100001,
                                13,
                                3,
                                1100001,
                                14,
                                2,
                                1100001,
                                15,
                                2
                            ],
                            "index": 3
                        },
                        {
                            "code": 401,
                            "codeStr": "ChoiceCase",
                            "intArgs": [
                                1
                            ],
                            "index": 4
                        },
                        {
                            "code": 121,
                            "codeStr": "SetVariable",
                            "intArgs": [
                                2800002,
                                13,
                                0,
                                0
                            ],
                            "index": 5
                        },
                        {
                            "code": 401,
                            "codeStr": "ChoiceCase",
                            "intArgs": [
                                2
                            ],
                            "index": 7
                        },
                        {
                            "code": 121,
                            "codeStr": "SetVariable",
                            "intArgs": [
                                2800002,
                                14,
                                0,
                                0
                            ],
                            "index": 8
                        },
                        {
                            "code": 401,
                            "codeStr": "ChoiceCase",
                            "intArgs": [
                                3
                            ],
                            "index": 10
                        },
                        {
                            "code": 121,
                            "codeStr": "SetVariable",
                            "intArgs": [
                                2800002,
                                15,
                                0,
                                0
                            ],
                            "index": 11
                        },
                        {
                            "code": 300,
                            "codeStr": "CommonEventByName",
                            "stringArgs": [
                                "場所移動"
                            ],
                            "intArgs": [
                                0,
                                52,
                                51,
                                2800002,
                                13,
                                8,
                                3000000,
                                3000000,
                                3000000
                            ],
                            "index": 14
                        },
                        {
                            "code": 300,
                            "codeStr": "CommonEventByName",
                            "stringArgs": [
                                "画面色調変更"
                            ],
                            "intArgs": [
                                0,
                                3,
                                4294967295,
                                10,
                                1
                            ],
                            "index": 15
                        }
                    ]
                }
            ]
        },
        {
            "id": 2,
            "name": "カラス",
            "pages": [
                {
                    "id": 0,
                    "list": [
                        {
                            "code": 300,
                            "codeStr": "CommonEventByName",
                            "stringArgs": [
                                "イベント当たり判定"
                            ],
                            "intArgs": [
                                0,
                                16777216,
                                2900053
                            ],
                            "index": 0
                        },
                        {
                            "code": 111,
                            "codeStr": "VariableCondition",
                            "intArgs": [
                                1,
                                2900053,
                                1,
                                2
                            ],
                            "index": 1
                        },
                        {
                            "code": 401,
                            "codeStr": "ChoiceCase",
                            "intArgs": [
                                1
                            ],
                            "index": 2
                        },
                        {
                            "code": 300,
                            "codeStr": "CommonEventByName",
                            "stringArgs": [
                                "セーブポイント"
                            ],
                            "intArgs": [
                                0,
                                0
                            ],
                            "index": 6
                        }
                    ]
                }
            ]
        },
        {
            "id": 3,
            "name": "カラスエフィクト",
            "pages": [
                {
                    "id": 0,
                    "list": [
                        {
                            "code": 300,
                            "codeStr": "CommonEventByName",
                            "stringArgs": [
                                "座標取得",
                                "anime_obj01",
                                "10",
                                "10",
                                "28"
                            ],
                            "intArgs": [
                                0,
                                61508,
                                7,
                                4294967285,
                                4294967286,
                                1,
                                0,
                                0,
                                0,
                                0
                            ],
                            "index": 0
                        },
                        {
                            "code": 300,
                            "codeStr": "CommonEventByName",
                            "stringArgs": [
                                "カラスエフィクト"
                            ],
                            "intArgs": [
                                0,
                                4,
                                2,
                                23,
                                1,
                                1
                            ],
                            "index": 1
                        },
                        {
                            "code": 173,
                            "codeStr": "EraseEvent",
                            "intArgs": [
                                4294967294,
                                0
                            ],
                            "index": 2
                        }
                    ]
                }
            ]
        },
        {
            "id": 4,
            "name": "灯火",
            "pages": [
                {
                    "id": 0,
                    "list": [
                        {
                            "code": 300,
                            "codeStr": "CommonEventByName",
                            "stringArgs": [
                                "パーティクル準備",
                                "",
                                "",
                                "4",
                                ""
                            ],
                            "intArgs": [
                                0,
                                16452,
                                0,
                                6,
                                4294967294,
                                5,
                                3000000,
                                3000000,
                                0,
                                3000000
                            ],
                            "index": 0
                        },
                        {
                            "code": 300,
                            "codeStr": "CommonEventByName",
                            "stringArgs": [
                                "ライティング"
                            ],
                            "intArgs": [
                                0,
                                20,
                                1,
                                300,
                                60,
                                1,
                                3000000
                            ],
                            "index": 1
                        },
                        {
                            "code": 173,
                            "codeStr": "EraseEvent",
                            "intArgs": [
                                4294967294,
                                0
                            ],
                            "index": 2
                        }
                    ]
                },
                {
                    "id": 1,
                    "list": [
                        {
                            "code": 300,
                            "codeStr": "CommonEventByName",
                            "stringArgs": [
                                "パーティクル準備",
                                "",
                                "",
                                "4",
                                ""
                            ],
                            "intArgs": [
                                0,
                                16452,
                                0,
                                6,
                                4294967294,
                                5,
                                3000000,
                                3000000,
                                0,
                                3000000
                            ],
                            "index": 0
                        },
                        {
                            "code": 300,
                            "codeStr": "CommonEventByName",
                            "stringArgs": [
                                "ライティング"
                            ],
                            "intArgs": [
                                0,
                                20,
                                1,
                                300,
                                60,
                                1,
                                3000000
                            ],
                            "index": 1
                        },
                        {
                            "code": 173,
                            "codeStr": "EraseEvent",
                            "intArgs": [
                                4294967294,
                                0
                            ],
                            "index": 2
                        }
                    ]
                }
            ]
        },
        {
            "id": 5,
            "name": "薔薇落ちる",
            "pages": [
                {
                    "id": 0,
                    "list": [
                        {
                            "code": 124,
                            "codeStr": "SetVariableEx",
                            "intArgs": [
                                1100001,
                                4096,
                                4294967294,
                                0
                            ],
                            "index": 0
                        },
                        {
                            "code": 124,
                            "codeStr": "SetVariableEx",
                            "intArgs": [
                                1100002,
                                4096,
                                4294967294,
                                1
                            ],
                            "index": 1
                        },
                        {
                            "code": 121,
                            "codeStr": "SetVariable",
                            "intArgs": [
                                1100001,
                                1000,
                                0,
                                768
                            ],
                            "index": 2
                        },
                        {
                            "code": 121,
                            "codeStr": "SetVariable",
                            "intArgs": [
                                1100001,
                                1100002,
                                0,
                                256
                            ],
                            "index": 3
                        },
                        {
                            "code": 111,
                            "codeStr": "VariableCondition",
                            "intArgs": [
                                2,
                                1100001,
                                19011,
                                2,
                                1100001,
                                20011,
                                2
                            ],
                            "index": 4
                        },
                        {
                            "code": 401,
                            "codeStr": "ChoiceCase",
                            "intArgs": [
                                1
                            ],
                            "index": 5
                        },
                        {
                            "code": 121,
                            "codeStr": "SetVariable",
                            "intArgs": [
                                1100000,
                                1,
                                0,
                                0
                            ],
                            "index": 6
                        },
                        {
                            "code": 401,
                            "codeStr": "ChoiceCase",
                            "intArgs": [
                                2
                            ],
                            "index": 8
                        },
                        {
                            "code": 121,
                            "codeStr": "SetVariable",
                            "intArgs": [
                                1100000,
                                1,
                                0,
                                0
                            ],
                            "index": 9
                        }
                    ]
                },
                {
                    "id": 1,
                    "list": [
                        {
                            "code": 242,
                            "codeStr": "Command",
                            "intArgs": [
                                3,
                                20,
                                9,
                                1,
                                1,
                                138
                            ],
                            "index": 0
                        },
                        {
                            "code": 242,
                            "codeStr": "Command",
                            "intArgs": [
                                3,
                                20,
                                10,
                                1,
                                1,
                                146
                            ],
                            "index": 1
                        },
                        {
                            "code": 180,
                            "codeStr": "Wait",
                            "intArgs": [
                                5
                            ],
                            "index": 2
                        },
                        {
                            "code": 242,
                            "codeStr": "Command",
                            "intArgs": [
                                3,
                                20,
                                10,
                                1,
                                1,
                                154
                            ],
                            "index": 3
                        },
                        {
                            "code": 180,
                            "codeStr": "Wait",
                            "intArgs": [
                                5
                            ],
                            "index": 4
                        },
                        {
                            "code": 242,
                            "codeStr": "Command",
                            "intArgs": [
                                3,
                                20,
                                10,
                                1,
                                1,
                                162
                            ],
                            "index": 5
                        },
                        {
                            "code": 121,
                            "codeStr": "SetVariable",
                            "intArgs": [
                                1100000,
                                2,
                                0,
                                0
                            ],
                            "index": 6
                        }
                    ]
                },
                {
                    "id": 2,
                    "list": [
                        {
                            "code": 242,
                            "codeStr": "Command",
                            "intArgs": [
                                3,
                                20,
                                9,
                                1,
                                1,
                                138
                            ],
                            "index": 0
                        },
                        {
                            "code": 242,
                            "codeStr": "Command",
                            "intArgs": [
                                3,
                                20,
                                10,
                                1,
                                1,
                                162
                            ],
                            "index": 1
                        },
                        {
                            "code": 121,
                            "codeStr": "SetVariable",
                            "intArgs": [
                                1100000,
                                2,
                                0,
                                0
                            ],
                            "index": 2
                        }
                    ]
                }
            ]
        },
        {
            "id": 6,
            "name": "はらぺこ",
            "pages": [
                {
                    "id": 0,
                    "list": [
                        {
                            "code": 300,
                            "codeStr": "CommonEventByName",
                            "stringArgs": [
                                "イベント当たり判定"
                            ],
                            "intArgs": [
                                0,
                                16777216,
                                2900053
                            ],
                            "index": 0
                        },
                        {
                            "code": 111,
                            "codeStr": "VariableCondition",
                            "intArgs": [
                                1,
                                2900053,
                                1,
                                2
                            ],
                            "index": 1
                        },
                        {
                            "code": 401,
                            "codeStr": "ChoiceCase",
                            "intArgs": [
                                1
                            ],
                            "index": 2
                        },
                        {
                            "code": 300,
                            "codeStr": "CommonEventByName",
                            "stringArgs": [
                                "イベント枠"
                            ],
                            "intArgs": [
                                0,
                                1,
                                1
                            ],
                            "index": 6
                        },
                        {
                            "code": 180,
                            "codeStr": "Wait",
                            "intArgs": [
                                50
                            ],
                            "index": 7
                        },
                        {
                            "code": 140,
                            "codeStr": "Sound",
                            "stringArgs": [
                                "SE/dousa_harapeko_lab.ogg"
                            ],
                            "intArgs": [
                                33554464,
                                0,
                                0,
                                0,
                                100,
                                100
                            ],
                            "index": 8
                        },
                        {
                            "code": 300,
                            "codeStr": "CommonEventByName",
                            "stringArgs": [
                                "立ち絵"
                            ],
                            "intArgs": [
                                0,
                                3,
                                37,
                                0,
                                0
                            ],
                            "index": 9
                        },
                        {
                            "code": 101,
                            "codeStr": "Message",
                            "stringArgs": [
                                "Я так... голоден."
                            ],
                            "index": 10
                        },
                        {
                            "code": 180,
                            "codeStr": "Wait",
                            "intArgs": [
                                20
                            ],
                            "index": 11
                        },
                        {
                            "code": 111,
                            "codeStr": "VariableCondition",
                            "intArgs": [
                                17,
                                2000021,
                                2,
                                2
                            ],
                            "index": 12
                        },
                        {
                            "code": 401,
                            "codeStr": "ChoiceCase",
                            "intArgs": [
                                1
                            ],
                            "index": 13
                        },
                        {
                            "code": 180,
                            "codeStr": "Wait",
                            "intArgs": [
                                50
                            ],
                            "index": 14
                        },
                        {
                            "code": 111,
                            "codeStr": "VariableCondition",
                            "intArgs": [
                                2,
                                2000001,
                                0,
                                2,
                                2000001,
                                1,
                                2
                            ],
                            "index": 15
                        },
                        {
                            "code": 401,
                            "codeStr": "ChoiceCase",
                            "intArgs": [
                                1
                            ],
                            "index": 16
                        },
                        {
                            "code": 300,
                            "codeStr": "CommonEventByName",
                            "stringArgs": [
                                "立ち絵"
                            ],
                            "intArgs": [
                                0,
                                3,
                                0,
                                0,
                                0
                            ],
                            "index": 17
                        },
                        {
                            "code": 101,
                            "codeStr": "Message",
                            "stringArgs": [
                                "Эм, может, тебе это понравится?"
                            ],
                            "index": 18
                        },
                        {
                            "code": 401,
                            "codeStr": "ChoiceCase",
                            "intArgs": [
                                2
                            ],
                            "index": 20
                        },
                        {
                            "code": 300,
                            "codeStr": "CommonEventByName",
                            "stringArgs": [
                                "立ち絵"
                            ],
                            "intArgs": [
                                0,
                                3,
                                9,
                                1,
                                0
                            ],
                            "index": 21
                        },
                        {
                            "code": 101,
                            "codeStr": "Message",
                            "stringArgs": [
                                "Не хочешь съесть их?"
                            ],
                            "index": 22
                        },
                        {
                            "code": 180,
                            "codeStr": "Wait",
                            "intArgs": [
                                20
                            ],
                            "index": 25
                        },
                        {
                            "code": 201,
                            "codeStr": "Move",
                            "intArgs": [
                                6
                            ],
                            "index": 26
                        },
                        {
                            "code": 180,
                            "codeStr": "Wait",
                            "intArgs": [
                                50
                            ],
                            "index": 27
                        },
                        {
                            "code": 300,
                            "codeStr": "CommonEventByName",
                            "stringArgs": [
                                "立ち絵"
                            ],
                            "intArgs": [
                                0,
                                3,
                                37,
                                0,
                                0
                            ],
                            "index": 28
                        },
                        {
                            "code": 101,
                            "codeStr": "Message",
                            "stringArgs": [
                                "...Ахх, пахнет прямо как мои любимые сосиски!"
                            ],
                            "index": 29
                        },
                        {
                            "code": 180,
                            "codeStr": "Wait",
                            "intArgs": [
                                10
                            ],
                            "index": 30
                        },
                        {
                            "code": 300,
                            "codeStr": "CommonEventByName",
                            "stringArgs": [
                                "画面色調変更"
                            ],
                            "intArgs": [
                                0,
                                4,
                                0,
                                20,
                                0,
                                100
                            ],
                            "index": 31
                        },
                        {
                            "code": 300,
                            "codeStr": "CommonEventByName",
                            "stringArgs": [
                                "座標取得",
                                "anime_ghost01",
                                "10",
                                "10",
                                "85"
                            ],
                            "intArgs": [
                                0,
                                61508,
                                4294967295,
                                4294967264,
                                1,
                                1,
                                0,
                                0,
                                0,
                                0
                            ],
                            "index": 32
                        },
                        {
                            "code": 121,
                            "codeStr": "SetVariable",
                            "intArgs": [
                                1000080,
                                1,
                                0,
                                0
                            ],
                            "index": 33
                        },
                        {
                            "code": 111,
                            "codeStr": "VariableCondition",
                            "intArgs": [
                                2,
                                2000001,
                                0,
                                2,
                                2000001,
                                1,
                                2
                            ],
                            "index": 34
                        },
                        {
                            "code": 401,
                            "codeStr": "ChoiceCase",
                            "intArgs": [
                                1
                            ],
                            "index": 35
                        },
                        {
                            "code": 201,
                            "codeStr": "Move",
                            "intArgs": [
                                4294967294
                            ],
                            "index": 36
                        },
                        {
                            "code": 401,
                            "codeStr": "ChoiceCase",
                            "intArgs": [
                                2
                            ],
                            "index": 38
                        },
                        {
                            "code": 201,
                            "codeStr": "Move",
                            "intArgs": [
                                4294967294
                            ],
                            "index": 39
                        },
                        {
                            "code": 130,
                            "codeStr": "Teleport",
                            "intArgs": [
                                4294967295,
                                17,
                                11,
                                4294967295,
                                0
                            ],
                            "index": 42
                        },
                        {
                            "code": 300,
                            "codeStr": "CommonEventByName",
                            "stringArgs": [
                                "画面色調変更"
                            ],
                            "intArgs": [
                                0,
                                4,
                                4294967295,
                                20,
                                0,
                                0
                            ],
                            "index": 43
                        },
                        {
                            "code": 180,
                            "codeStr": "Wait",
                            "intArgs": [
                                200
                            ],
                            "index": 44
                        },
                        {
                            "code": 300,
                            "codeStr": "CommonEventByName",
                            "stringArgs": [
                                "立ち絵"
                            ],
                            "intArgs": [
                                0,
                                3,
                                37,
                                1,
                                0
                            ],
                            "index": 45
                        },
                        {
                            "code": 101,
                            "codeStr": "Message",
                            "stringArgs": [
                                "Ммм...\nТак вкусно!.."
                            ],
                            "index": 46
                        },
                        {
                            "code": 101,
                            "codeStr": "Message",
                            "stringArgs": [
                                "На вкус почти как те, что делала мама..."
                            ],
                            "index": 47
                        },
                        {
                            "code": 180,
                            "codeStr": "Wait",
                            "intArgs": [
                                100
                            ],
                            "index": 48
                        },
                        {
                            "code": 300,
                            "codeStr": "CommonEventByName",
                            "stringArgs": [
                                "画面色調変更"
                            ],
                            "intArgs": [
                                0,
                                3,
                                0,
                                20,
                                0
                            ],
                            "index": 49
                        },
                        {
                            "code": 121,
                            "codeStr": "SetVariable",
                            "intArgs": [
                                1000080,
                                2,
                                0,
                                0
                            ],
                            "index": 50
                        },
                        {
                            "code": 290,
                            "codeStr": "Effect",
                            "intArgs": [
                                160,
                                0,
                                1,
                                1,
                                90,
                                91,
                                0
                            ],
                            "index": 51
                        },
                        {
                            "code": 150,
                            "codeStr": "Picture",
                            "intArgs": [
                                2,
                                1,
                                0
                            ],
                            "index": 52
                        },
                        {
                            "code": 130,
                            "codeStr": "Teleport",
                            "intArgs": [
                                4294967294,
                                18,
                                11,
                                0,
                                0
                            ],
                            "index": 53
                        },
                        {
                            "code": 201,
                            "codeStr": "Move",
                            "intArgs": [
                                4294967295
                            ],
                            "index": 54
                        },
                        {
                            "code": 201,
                            "codeStr": "Move",
                            "intArgs": [
                                4294967294
                            ],
                            "index": 55
                        },
                        {
                            "code": 180,
                            "codeStr": "Wait",
                            "intArgs": [
                                100
                            ],
                            "index": 56
                        },
                        {
                            "code": 300,
                            "codeStr": "CommonEventByName",
                            "stringArgs": [
                                "画面色調変更"
                            ],
                            "intArgs": [
                                0,
                                3,
                                4294967295,
                                20,
                                0
                            ],
                            "index": 57
                        },
                        {
                            "code": 180,
                            "codeStr": "Wait",
                            "intArgs": [
                                70
                            ],
                            "index": 58
                        },
                        {
                            "code": 300,
                            "codeStr": "CommonEventByName",
                            "stringArgs": [
                                "立ち絵"
                            ],
                            "intArgs": [
                                0,
                                3,
                                37,
                                1,
                                0
                            ],
                            "index": 59
                        },
                        {
                            "code": 101,
                            "codeStr": "Message",
                            "stringArgs": [
                                "Ну, до маминых высот не дотягивает,\nно было очень вкусно."
                            ],
                            "index": 60
                        },
                        {
                            "code": 101,
                            "codeStr": "Message",
                            "stringArgs": [
                                "Я не ел ни крохи еды с тех пор,\nкак меня здесь заперли."
                            ],
                            "index": 61
                        },
                        {
                            "code": 101,
                            "codeStr": "Message",
                            "stringArgs": [
                                "Я голодал!"
                            ],
                            "index": 62
                        },
                        {
                            "code": 111,
                            "codeStr": "VariableCondition",
                            "intArgs": [
                                1,
                                2000001,
                                0,
                                2
                            ],
                            "index": 63
                        },
                        {
                            "code": 401,
                            "codeStr": "ChoiceCase",
                            "intArgs": [
                                1
                            ],
                            "index": 64
                        },
                        {
                            "code": 201,
                            "codeStr": "Move",
                            "intArgs": [
                                4294967294
                            ],
                            "index": 65
                        },
                        {
                            "code": 300,
                            "codeStr": "CommonEventByName",
                            "stringArgs": [
                                "立ち絵"
                            ],
                            "intArgs": [
                                0,
                                3,
                                0,
                                0,
                                0
                            ],
                            "index": 66
                        },
                        {
                            "code": 101,
                            "codeStr": "Message",
                            "stringArgs": [
                                "Мария же всегда приносила\nеду в подвал..."
                            ],
                            "index": 67
                        },
                        {
                            "code": 101,
                            "codeStr": "Message",
                            "stringArgs": [
                                "Тебе ничего не доставалось?"
                            ],
                            "index": 68
                        },
                        {
                            "code": 300,
                            "codeStr": "CommonEventByName",
                            "stringArgs": [
                                "立ち絵"
                            ],
                            "intArgs": [
                                0,
                                3,
                                37,
                                0,
                                0
                            ],
                            "index": 69
                        },
                        {
                            "code": 101,
                            "codeStr": "Message",
                            "stringArgs": [
                                "Все, кроме меня, получали еду..."
                            ],
                            "index": 70
                        },
                        {
                            "code": 300,
                            "codeStr": "CommonEventByName",
                            "stringArgs": [
                                "座標取得",
                                "anime_ghost01",
                                "10",
                                "10",
                                "87"
                            ],
                            "intArgs": [
                                0,
                                61508,
                                4294967295,
                                4294967264,
                                4294967295,
                                0,
                                0,
                                0,
                                0,
                                0
                            ],
                            "index": 71
                        },
                        {
                            "code": 180,
                            "codeStr": "Wait",
                            "intArgs": [
                                50
                            ],
                            "index": 72
                        },
                        {
                            "code": 300,
                            "codeStr": "CommonEventByName",
                            "stringArgs": [
                                "立ち絵"
                            ],
                            "intArgs": [
                                0,
                                3,
                                37,
                                0,
                                0
                            ],
                            "index": 73
                        },
                        {
                            "code": 101,
                            "codeStr": "Message",
                            "stringArgs": [
                                "Я никогда никому не был нужен..."
                            ],
                            "index": 74
                        },
                        {
                            "code": 101,
                            "codeStr": "Message",
                            "stringArgs": [
                                "Я бесполезен и только и делал,\nчто всех бесил, потому обо мне и позабыли."
                            ],
                            "index": 75
                        },
                        {
                            "code": 180,
                            "codeStr": "Wait",
                            "intArgs": [
                                50
                            ],
                            "index": 76
                        },
                        {
                            "code": 201,
                            "codeStr": "Move",
                            "intArgs": [
                                4294967294
                            ],
                            "index": 77
                        },
                        {
                            "code": 180,
                            "codeStr": "Wait",
                            "intArgs": [
                                50
                            ],
                            "index": 78
                        },
                        {
                            "code": 150,
                            "codeStr": "Picture",
                            "intArgs": [
                                2,
                                4294967295,
                                0,
                                1
                            ],
                            "index": 79
                        },
                        {
                            "code": 201,
                            "codeStr": "Move",
                            "intArgs": [
                                4294967295
                            ],
                            "index": 80
                        },
                        {
                            "code": 300,
                            "codeStr": "CommonEventByName",
                            "stringArgs": [
                                "感情表現アイコン"
                            ],
                            "intArgs": [
                                0,
                                4,
                                4294967295,
                                0,
                                0,
                                0
                            ],
                            "index": 81
                        },
                        {
                            "code": 180,
                            "codeStr": "Wait",
                            "intArgs": [
                                80
                            ],
                            "index": 82
                        },
                        {
                            "code": 201,
                            "codeStr": "Move",
                            "intArgs": [
                                4294967295
                            ],
                            "index": 85
                        },
                        {
                            "code": 300,
                            "codeStr": "CommonEventByName",
                            "stringArgs": [
                                "座標取得",
                                "anime_ghost01",
                                "10",
                                "10",
                                "88"
                            ],
                            "intArgs": [
                                0,
                                61508,
                                4294967295,
                                4294967264,
                                4294967295,
                                0,
                                0,
                                0,
                                0,
                                0
                            ],
                            "index": 86
                        },
                        {
                            "code": 180,
                            "codeStr": "Wait",
                            "intArgs": [
                                20
                            ],
                            "index": 87
                        },
                        {
                            "code": 300,
                            "codeStr": "CommonEventByName",
                            "stringArgs": [
                                "立ち絵"
                            ],
                            "intArgs": [
                                0,
                                3,
                                37,
                                1,
                                0
                            ],
                            "index": 88
                        },
                        {
                            "code": 101,
                            "codeStr": "Message",
                            "stringArgs": [
                                "Держи."
                            ],
                            "index": 89
                        },
                        {
                            "code": 111,
                            "codeStr": "VariableCondition",
                            "intArgs": [
                                1,
                                2000001,
                                0,
                                2
                            ],
                            "index": 90
                        },
                        {
                            "code": 401,
                            "codeStr": "ChoiceCase",
                            "intArgs": [
                                1
                            ],
                            "index": 91
                        },
                        {
                            "code": 201,
                            "codeStr": "Move",
                            "intArgs": [
                                4294967294
                            ],
                            "index": 92
                        },
                        {
                            "code": 180,
                            "codeStr": "Wait",
                            "intArgs": [
                                20
                            ],
                            "index": 95
                        },
                        {
                            "code": 150,
                            "codeStr": "Picture",
                            "intArgs": [
                                4263681,
                                4294967295,
                                20,
                                0,
                                0,
                                4293967296,
                                4293967296,
                                4294967286,
                                0,
                                4293967296,
                                4293967296,
                                0,
                                16777216
                            ],
                            "index": 96
                        },
                        {
                            "code": 150,
                            "codeStr": "Picture",
                            "intArgs": [
                                4263681,
                                4294967295,
                                0,
                                0,
                                0,
                                89,
                                4293967296,
                                0,
                                0,
                                4293967296,
                                4293967296,
                                0,
                                16777216,
                                20
                            ],
                            "index": 97
                        },
                        {
                            "code": 150,
                            "codeStr": "Picture",
                            "intArgs": [
                                4263681,
                                4294967295,
                                20,
                                0,
                                0,
                                4293967296,
                                4293967296,
                                10,
                                0,
                                4293967296,
                                4293967296,
                                0,
                                16777216,
                                21
                            ],
                            "index": 98
                        },
                        {
                            "code": 150,
                            "codeStr": "Picture",
                            "intArgs": [
                                69378,
                                4294967295,
                                0,
                                41
                            ],
                            "index": 99
                        },
                        {
                            "code": 111,
                            "codeStr": "VariableCondition",
                            "intArgs": [
                                2,
                                2000001,
                                0,
                                2,
                                2000001,
                                1,
                                2
                            ],
                            "index": 100
                        },
                        {
                            "code": 401,
                            "codeStr": "ChoiceCase",
                            "intArgs": [
                                1
                            ],
                            "index": 101
                        },
                        {
                            "code": 201,
                            "codeStr": "Move",
                            "intArgs": [
                                4294967294
                            ],
                            "index": 102
                        },
                        {
                            "code": 401,
                            "codeStr": "ChoiceCase",
                            "intArgs": [
                                2
                            ],
                            "index": 104
                        },
                        {
                            "code": 201,
                            "codeStr": "Move",
                            "intArgs": [
                                4294967294
                            ],
                            "index": 105
                        },
                        {
                            "code": 201,
                            "codeStr": "Move",
                            "intArgs": [
                                4294967295
                            ],
                            "index": 108
                        },
                        {
                            "code": 180,
                            "codeStr": "Wait",
                            "intArgs": [
                                20
                            ],
                            "index": 109
                        },
                        {
                            "code": 300,
                            "codeStr": "CommonEventByName",
                            "stringArgs": [
                                "アイテム入手"
                            ],
                            "intArgs": [
                                0,
                                4,
                                16,
                                4294967295,
                                0,
                                0
                            ],
                            "index": 110
                        },
                        {
                            "code": 300,
                            "codeStr": "CommonEventByName",
                            "stringArgs": [
                                "座標取得",
                                "anime_ghost01",
                                "10",
                                "10",
                                "90"
                            ],
                            "intArgs": [
                                0,
                                61508,
                                4294967295,
                                4294967264,
                                4294967295,
                                0,
                                0,
                                0,
                                0,
                                0
                            ],
                            "index": 111
                        },
                        {
                            "code": 290,
                            "codeStr": "Effect",
                            "intArgs": [
                                160,
                                10,
                                4294967295,
                                4294967295,
                                90,
                                91,
                                0
                            ],
                            "index": 112
                        },
                        {
                            "code": 300,
                            "codeStr": "CommonEventByName",
                            "stringArgs": [
                                "立ち絵"
                            ],
                            "intArgs": [
                                0,
                                3,
                                37,
                                1,
                                0
                            ],
                            "index": 113
                        },
                        {
                            "code": 101,
                            "codeStr": "Message",
                            "stringArgs": [
                                "<C>Ну, знаешь...\n<C>В благодарность за вкусную еду."
                            ],
                            "index": 114
                        },
                        {
                            "code": 101,
                            "codeStr": "Message",
                            "stringArgs": [
                                "Эээ... ну, эм..."
                            ],
                            "index": 115
                        },
                        {
                            "code": 290,
                            "codeStr": "Effect",
                            "intArgs": [
                                160,
                                0,
                                4294967295,
                                4294967295,
                                90,
                                91,
                                0
                            ],
                            "index": 116
                        },
                        {
                            "code": 150,
                            "codeStr": "Picture",
                            "intArgs": [
                                4263681,
                                4294967295,
                                0,
                                0,
                                0,
                                92,
                                4293967296,
                                0,
                                0,
                                4293967296,
                                4293967296,
                                0,
                                16777216
                            ],
                            "index": 117
                        },
                        {
                            "code": 101,
                            "codeStr": "Message",
                            "stringArgs": [
                                "...Спасибо, наверное."
                            ],
                            "index": 118
                        },
                        {
                            "code": 180,
                            "codeStr": "Wait",
                            "intArgs": [
                                50
                            ],
                            "index": 119
                        },
                        {
                            "code": 300,
                            "codeStr": "CommonEventByName",
                            "stringArgs": [
                                "ショートカット"
                            ],
                            "intArgs": [
                                0,
                                18,
                                0,
                                0,
                                3000000
                            ],
                            "index": 120
                        },
                        {
                            "code": 111,
                            "codeStr": "VariableCondition",
                            "intArgs": [
                                1,
                                2000001,
                                0,
                                2
                            ],
                            "index": 121
                        },
                        {
                            "code": 401,
                            "codeStr": "ChoiceCase",
                            "intArgs": [
                                1
                            ],
                            "index": 122
                        },
                        {
                            "code": 300,
                            "codeStr": "CommonEventByName",
                            "stringArgs": [
                                "立ち絵"
                            ],
                            "intArgs": [
                                0,
                                3,
                                0,
                                4,
                                0
                            ],
                            "index": 123
                        },
                        {
                            "code": 101,
                            "codeStr": "Message",
                            "stringArgs": [
                                "Ага..."
                            ],
                            "index": 124
                        },
                        {
                            "code": 150,
                            "codeStr": "Picture",
                            "intArgs": [
                                2,
                                4294967295,
                                50
                            ],
                            "index": 127
                        },
                        {
                            "code": 180,
                            "codeStr": "Wait",
                            "intArgs": [
                                100
                            ],
                            "index": 128
                        },
                        {
                            "code": 121,
                            "codeStr": "SetVariable",
                            "intArgs": [
                                2900006,
                                1,
                                0,
                                0
                            ],
                            "index": 129
                        },
                        {
                            "code": 300,
                            "codeStr": "CommonEventByName",
                            "stringArgs": [
                                "ミッション"
                            ],
                            "intArgs": [
                                0,
                                4,
                                19,
                                4294967295,
                                0,
                                1
                            ],
                            "index": 130
                        },
                        {
                            "code": 300,
                            "codeStr": "CommonEventByName",
                            "stringArgs": [
                                "システムアイコン"
                            ],
                            "intArgs": [
                                0,
                                2,
                                1,
                                1
                            ],
                            "index": 131
                        },
                        {
                            "code": 300,
                            "codeStr": "CommonEventByName",
                            "stringArgs": [
                                "システムアイコン"
                            ],
                            "intArgs": [
                                0,
                                2,
                                2,
                                1
                            ],
                            "index": 132
                        },
                        {
                            "code": 10001,
                            "codeStr": "Command",
                            "stringArgs": [
                                "10"
                            ],
                            "intArgs": [
                                19
                            ],
                            "index": 133
                        },
                        {
                            "code": 121,
                            "codeStr": "SetVariable",
                            "intArgs": [
                                2000021,
                                3,
                                0,
                                0
                            ],
                            "index": 134
                        },
                        {
                            "code": 300,
                            "codeStr": "CommonEventByName",
                            "stringArgs": [
                                "イベント枠"
                            ],
                            "intArgs": [
                                0,
                                1,
                                0
                            ],
                            "index": 135
                        },
                        {
                            "code": 121,
                            "codeStr": "SetVariable",
                            "intArgs": [
                                1000090,
                                1,
                                0,
                                0
                            ],
                            "index": 136
                        },
                        {
                            "code": 173,
                            "codeStr": "EraseEvent",
                            "intArgs": [
                                4294967294,
                                0
                            ],
                            "index": 137
                        },
                        {
                            "code": 420,
                            "codeStr": "ElseCase",
                            "intArgs": [
                                0
                            ],
                            "index": 139
                        },
                        {
                            "code": 300,
                            "codeStr": "CommonEventByName",
                            "stringArgs": [
                                "ミッション"
                            ],
                            "intArgs": [
                                0,
                                4,
                                19,
                                4294967295,
                                1,
                                1
                            ],
                            "index": 140
                        },
                        {
                            "code": 300,
                            "codeStr": "CommonEventByName",
                            "stringArgs": [
                                "イベント枠"
                            ],
                            "intArgs": [
                                0,
                                1,
                                0
                            ],
                            "index": 141
                        }
                    ]
                },
                {
                    "id": 1,
                    "list": [
                        {
                            "code": 210,
                            "codeStr": "CommonEvent",
                            "intArgs": [
                                4294967295,
                                0
                            ],
                            "index": 0
                        }
                    ]
                }
            ]
        },
        {
            "id": 7,
            "name": "ポット",
            "pages": [
                {
                    "id": 0,
                    "list": [
                        {
                            "code": 121,
                            "codeStr": "SetVariable",
                            "intArgs": [
                                1100000,
                                1,
                                0,
                                0
                            ],
                            "index": 0
                        }
                    ]
                },
                {
                    "id": 1,
                    "list": [
                        {
                            "code": 140,
                            "codeStr": "Sound",
                            "stringArgs": [
                                "SE/seikatsu_galass_cup_lab.ogg"
                            ],
                            "intArgs": [
                                33554464,
                                0,
                                0,
                                0,
                                100,
                                100
                            ],
                            "index": 0
                        },
                        {
                            "code": 150,
                            "codeStr": "Picture",
                            "intArgs": [
                                4263681,
                                4294967286,
                                5,
                                0,
                                0,
                                4293967296,
                                4293967296,
                                0,
                                0,
                                4293967296,
                                4294967096,
                                0,
                                16777216
                            ],
                            "index": 1
                        },
                        {
                            "code": 150,
                            "codeStr": "Picture",
                            "intArgs": [
                                4263681,
                                4294967286,
                                10,
                                0,
                                0,
                                4293967296,
                                4293967296,
                                0,
                                0,
                                4293967296,
                                200,
                                0,
                                16777216,
                                5
                            ],
                            "index": 2
                        },
                        {
                            "code": 150,
                            "codeStr": "Picture",
                            "intArgs": [
                                4263681,
                                4294967286,
                                5,
                                0,
                                0,
                                4293967296,
                                4293967296,
                                0,
                                0,
                                4293967296,
                                0,
                                0,
                                16777216,
                                15
                            ],
                            "index": 3
                        },
                        {
                            "code": 121,
                            "codeStr": "SetVariable",
                            "intArgs": [
                                1100000,
                                2,
                                0,
                                0
                            ],
                            "index": 4
                        },
                        {
                            "code": 173,
                            "codeStr": "EraseEvent",
                            "intArgs": [
                                4294967294,
                                0
                            ],
                            "index": 5
                        }
                    ]
                }
            ]
        },
        {
            "id": 8,
            "name": "ソテー",
            "pages": [
                {
                    "id": 0,
                    "list": [
                        {
                            "code": 150,
                            "codeStr": "Picture",
                            "intArgs": [
                                4263681,
                                1,
                                0,
                                0,
                                0,
                                86,
                                4293967296,
                                0,
                                0,
                                4293967296,
                                4293967296,
                                0,
                                16777216,
                                10
                            ],
                            "index": 0
                        },
                        {
                            "code": 150,
                            "codeStr": "Picture",
                            "intArgs": [
                                4263681,
                                1,
                                0,
                                0,
                                0,
                                85,
                                4293967296,
                                0,
                                0,
                                4293967296,
                                4293967296,
                                0,
                                16777216,
                                20
                            ],
                            "index": 1
                        },
                        {
                            "code": 150,
                            "codeStr": "Picture",
                            "intArgs": [
                                4263681,
                                1,
                                0,
                                0,
                                0,
                                86,
                                4293967296,
                                0,
                                0,
                                4293967296,
                                4293967296,
                                0,
                                16777216,
                                30
                            ],
                            "index": 2
                        },
                        {
                            "code": 150,
                            "codeStr": "Picture",
                            "intArgs": [
                                4263681,
                                1,
                                0,
                                0,
                                0,
                                85,
                                4293967296,
                                0,
                                0,
                                4293967296,
                                4293967296,
                                0,
                                16777216,
                                40
                            ],
                            "index": 3
                        },
                        {
                            "code": 180,
                            "codeStr": "Wait",
                            "intArgs": [
                                60
                            ],
                            "index": 4
                        }
                    ]
                },
                {
                    "id": 1,
                    "list": []
                }
            ]
        },
        {
            "id": 9,
            "name": "松明消える",
            "pages": [
                {
                    "id": 0,
                    "list": [
                        {
                            "code": 150,
                            "codeStr": "Picture",
                            "intArgs": [
                                2,
                                2004,
                                0
                            ],
                            "index": 0
                        },
                        {
                            "code": 300,
                            "codeStr": "CommonEventByName",
                            "stringArgs": [
                                "パーティクル準備"
                            ],
                            "intArgs": [
                                0,
                                68,
                                4294967295,
                                4294967294,
                                4294967295,
                                0,
                                3000000,
                                3000000,
                                3000000,
                                3000000
                            ],
                            "index": 1
                        },
                        {
                            "code": 140,
                            "codeStr": "Sound",
                            "stringArgs": [
                                "SE/eff_fire_kesu_lab.ogg"
                            ],
                            "intArgs": [
                                33554464,
                                0,
                                0,
                                0,
                                100,
                                100
                            ],
                            "index": 2
                        },
                        {
                            "code": 140,
                            "codeStr": "Sound",
                            "intArgs": [
                                16776976,
                                10,
                                0,
                                0
                            ],
                            "index": 3
                        },
                        {
                            "code": 121,
                            "codeStr": "SetVariable",
                            "intArgs": [
                                1000040,
                                1,
                                0,
                                0
                            ],
                            "index": 4
                        },
                        {
                            "code": 121,
                            "codeStr": "SetVariable",
                            "intArgs": [
                                1000100,
                                1,
                                0,
                                0
                            ],
                            "index": 5
                        },
                        {
                            "code": 121,
                            "codeStr": "SetVariable",
                            "intArgs": [
                                1100000,
                                2,
                                0,
                                0
                            ],
                            "index": 6
                        },
                        {
                            "code": 173,
                            "codeStr": "EraseEvent",
                            "intArgs": [
                                4294967294,
                                0
                            ],
                            "index": 7
                        }
                    ]
                }
            ]
        },
        {
            "id": 10,
            "name": "たいまつの音",
            "pages": [
                {
                    "id": 0,
                    "list": [
                        {
                            "code": 300,
                            "codeStr": "CommonEventByName",
                            "stringArgs": [
                                "接近コモン"
                            ],
                            "intArgs": [
                                0,
                                16777216,
                                1100001
                            ],
                            "index": 0
                        },
                        {
                            "code": 111,
                            "codeStr": "VariableCondition",
                            "intArgs": [
                                2,
                                1100001,
                                0,
                                2,
                                1100001,
                                1,
                                2
                            ],
                            "index": 1
                        },
                        {
                            "code": 401,
                            "codeStr": "ChoiceCase",
                            "intArgs": [
                                1
                            ],
                            "index": 2
                        },
                        {
                            "code": 140,
                            "codeStr": "Sound",
                            "intArgs": [
                                16776976,
                                50,
                                0,
                                0
                            ],
                            "index": 3
                        },
                        {
                            "code": 401,
                            "codeStr": "ChoiceCase",
                            "intArgs": [
                                2
                            ],
                            "index": 5
                        },
                        {
                            "code": 140,
                            "codeStr": "Sound",
                            "stringArgs": [
                                "BGS/shizen_bonfire_jiten.ogg"
                            ],
                            "intArgs": [
                                33554448,
                                50,
                                0,
                                0,
                                50,
                                100,
                                0
                            ],
                            "index": 6
                        }
                    ]
                },
                {
                    "id": 1,
                    "list": [
                        {
                            "code": 300,
                            "codeStr": "CommonEventByName",
                            "stringArgs": [
                                "接近コモン"
                            ],
                            "intArgs": [
                                0,
                                16777216,
                                1100001
                            ],
                            "index": 0
                        },
                        {
                            "code": 111,
                            "codeStr": "VariableCondition",
                            "intArgs": [
                                2,
                                1100001,
                                0,
                                2,
                                1100001,
                                1,
                                2
                            ],
                            "index": 1
                        },
                        {
                            "code": 401,
                            "codeStr": "ChoiceCase",
                            "intArgs": [
                                1
                            ],
                            "index": 2
                        },
                        {
                            "code": 140,
                            "codeStr": "Sound",
                            "intArgs": [
                                16776976,
                                50,
                                0,
                                0
                            ],
                            "index": 3
                        },
                        {
                            "code": 401,
                            "codeStr": "ChoiceCase",
                            "intArgs": [
                                2
                            ],
                            "index": 5
                        },
                        {
                            "code": 140,
                            "codeStr": "Sound",
                            "stringArgs": [
                                "BGS/shizen_bonfire_jiten.ogg"
                            ],
                            "intArgs": [
                                33554448,
                                50,
                                0,
                                0,
                                50,
                                100,
                                0
                            ],
                            "index": 6
                        }
                    ]
                }
            ]
        }
    ]
}