{
    "events": [
        {
            "id": 0,
            "name": "移動：1",
            "pages": [
                {
                    "id": 0,
                    "list": [
                        {
                            "code": 300,
                            "codeStr": "CommonEventByName",
                            "stringArgs": [
                                "場所移動"
                            ],
                            "intArgs": [
                                0,
                                52,
                                95,
                                13,
                                6,
                                2,
                                3000000,
                                3000000,
                                3000000
                            ],
                            "index": 0
                        }
                    ]
                }
            ]
        },
        {
            "id": 1,
            "name": "移動：2",
            "pages": [
                {
                    "id": 0,
                    "list": [
                        {
                            "code": 300,
                            "codeStr": "CommonEventByName",
                            "stringArgs": [
                                "場所移動"
                            ],
                            "intArgs": [
                                0,
                                52,
                                97,
                                29,
                                21,
                                4,
                                3000000,
                                3000000,
                                3000000
                            ],
                            "index": 0
                        }
                    ]
                }
            ]
        },
        {
            "id": 2,
            "name": "並列",
            "pages": [
                {
                    "id": 0,
                    "list": [
                        {
                            "code": 150,
                            "codeStr": "Picture",
                            "intArgs": [
                                16777218,
                                3000,
                                0,
                                0,
                                0,
                                3001
                            ],
                            "index": 0
                        },
                        {
                            "code": 300,
                            "codeStr": "CommonEventByName",
                            "stringArgs": [
                                "ライティングマップ"
                            ],
                            "intArgs": [
                                0,
                                20,
                                1,
                                1,
                                27,
                                8,
                                3000000
                            ],
                            "index": 1
                        },
                        {
                            "code": 300,
                            "codeStr": "CommonEventByName",
                            "stringArgs": [
                                "ライティングマップ"
                            ],
                            "intArgs": [
                                0,
                                20,
                                1,
                                2,
                                17,
                                8,
                                3000000
                            ],
                            "index": 2
                        },
                        {
                            "code": 300,
                            "codeStr": "CommonEventByName",
                            "stringArgs": [
                                "オートセーブ"
                            ],
                            "intArgs": [
                                0,
                                0
                            ],
                            "index": 3
                        },
                        {
                            "code": 173,
                            "codeStr": "EraseEvent",
                            "intArgs": [
                                4294967294,
                                0
                            ],
                            "index": 4
                        }
                    ]
                }
            ]
        },
        {
            "id": 3,
            "name": "人形赤 ",
            "pages": [
                {
                    "id": 0,
                    "list": [
                        {
                            "code": 210,
                            "codeStr": "CommonEvent",
                            "intArgs": [
                                500106,
                                16777220,
                                4294967295,
                                5,
                                600,
                                3000,
                                1100000
                            ],
                            "index": 0
                        }
                    ]
                },
                {
                    "id": 1,
                    "list": [
                        {
                            "code": 300,
                            "codeStr": "CommonEventByName",
                            "stringArgs": [
                                "かくれんぼ"
                            ],
                            "intArgs": [
                                0,
                                20,
                                0,
                                0,
                                46,
                                38,
                                3000000
                            ],
                            "index": 0
                        }
                    ]
                }
            ]
        },
        {
            "id": 4,
            "name": "人形緑",
            "pages": [
                {
                    "id": 0,
                    "list": [
                        {
                            "code": 210,
                            "codeStr": "CommonEvent",
                            "intArgs": [
                                500106,
                                16777220,
                                4294967295,
                                6,
                                600,
                                3001,
                                1100000
                            ],
                            "index": 0
                        }
                    ]
                },
                {
                    "id": 1,
                    "list": [
                        {
                            "code": 210,
                            "codeStr": "CommonEvent",
                            "intArgs": [
                                500106,
                                16777220,
                                4294967295,
                                6,
                                600,
                                3001,
                                1100000
                            ],
                            "index": 0
                        }
                    ]
                },
                {
                    "id": 2,
                    "list": [
                        {
                            "code": 300,
                            "codeStr": "CommonEventByName",
                            "stringArgs": [
                                "かくれんぼ"
                            ],
                            "intArgs": [
                                0,
                                20,
                                0,
                                1,
                                34,
                                15,
                                3000000
                            ],
                            "index": 0
                        },
                        {
                            "code": 121,
                            "codeStr": "SetVariable",
                            "intArgs": [
                                1100002,
                                2,
                                0,
                                0
                            ],
                            "index": 1
                        }
                    ]
                },
                {
                    "id": 3,
                    "list": [
                        {
                            "code": 111,
                            "codeStr": "VariableCondition",
                            "intArgs": [
                                1,
                                2900007,
                                0,
                                2
                            ],
                            "index": 0
                        },
                        {
                            "code": 401,
                            "codeStr": "ChoiceCase",
                            "intArgs": [
                                1
                            ],
                            "index": 1
                        },
                        {
                            "code": 210,
                            "codeStr": "CommonEvent",
                            "stringArgs": [
                                "",
                                "Не шевелится."
                            ],
                            "intArgs": [
                                500000,
                                4113,
                                4294967293,
                                3000000
                            ],
                            "index": 2
                        }
                    ]
                }
            ]
        },
        {
            "id": 5,
            "name": "壁崩壊",
            "pages": [
                {
                    "id": 0,
                    "list": [
                        {
                            "code": 130,
                            "codeStr": "Teleport",
                            "intArgs": [
                                4,
                                17,
                                6,
                                0,
                                0
                            ],
                            "index": 0
                        },
                        {
                            "code": 121,
                            "codeStr": "SetVariable",
                            "intArgs": [
                                1000042,
                                1,
                                0,
                                0
                            ],
                            "index": 1
                        },
                        {
                            "code": 121,
                            "codeStr": "SetVariable",
                            "intArgs": [
                                1100000,
                                1,
                                0,
                                0
                            ],
                            "index": 2
                        }
                    ]
                },
                {
                    "id": 1,
                    "list": [
                        {
                            "code": 140,
                            "codeStr": "Sound",
                            "stringArgs": [
                                "SE/break_glass _lab.ogg"
                            ],
                            "intArgs": [
                                33554464,
                                0,
                                0,
                                0,
                                100,
                                100
                            ],
                            "index": 0
                        },
                        {
                            "code": 242,
                            "codeStr": "Command",
                            "intArgs": [
                                1,
                                17,
                                5,
                                1,
                                1,
                                323
                            ],
                            "index": 1
                        },
                        {
                            "code": 242,
                            "codeStr": "Command",
                            "intArgs": [
                                1,
                                17,
                                6,
                                1,
                                1,
                                331
                            ],
                            "index": 2
                        },
                        {
                            "code": 121,
                            "codeStr": "SetVariable",
                            "intArgs": [
                                1000060,
                                1,
                                0,
                                0
                            ],
                            "index": 3
                        },
                        {
                            "code": 121,
                            "codeStr": "SetVariable",
                            "intArgs": [
                                1100000,
                                2,
                                0,
                                0
                            ],
                            "index": 4
                        },
                        {
                            "code": 173,
                            "codeStr": "EraseEvent",
                            "intArgs": [
                                4294967294,
                                0
                            ],
                            "index": 5
                        }
                    ]
                },
                {
                    "id": 2,
                    "list": [
                        {
                            "code": 242,
                            "codeStr": "Command",
                            "intArgs": [
                                1,
                                17,
                                5,
                                1,
                                1,
                                323
                            ],
                            "index": 0
                        },
                        {
                            "code": 242,
                            "codeStr": "Command",
                            "intArgs": [
                                1,
                                17,
                                6,
                                1,
                                1,
                                331
                            ],
                            "index": 1
                        },
                        {
                            "code": 173,
                            "codeStr": "EraseEvent",
                            "intArgs": [
                                4294967294,
                                0
                            ],
                            "index": 2
                        }
                    ]
                }
            ]
        },
        {
            "id": 6,
            "name": "床硝子",
            "pages": [
                {
                    "id": 0,
                    "list": [
                        {
                            "code": 140,
                            "codeStr": "Sound",
                            "stringArgs": [
                                "SE/break_glass_crack_lab.ogg"
                            ],
                            "intArgs": [
                                33554464,
                                0,
                                0,
                                0,
                                100,
                                100
                            ],
                            "index": 0
                        },
                        {
                            "code": 121,
                            "codeStr": "SetVariable",
                            "intArgs": [
                                1100000,
                                2,
                                0,
                                0
                            ],
                            "index": 1
                        }
                    ]
                },
                {
                    "id": 1,
                    "list": [
                        {
                            "code": 140,
                            "codeStr": "Sound",
                            "stringArgs": [
                                "SE/break_glass_crack_lab.ogg"
                            ],
                            "intArgs": [
                                33554464,
                                0,
                                0,
                                0,
                                100,
                                100
                            ],
                            "index": 0
                        },
                        {
                            "code": 121,
                            "codeStr": "SetVariable",
                            "intArgs": [
                                1100000,
                                3,
                                0,
                                0
                            ],
                            "index": 1
                        }
                    ]
                },
                {
                    "id": 2,
                    "list": [
                        {
                            "code": 140,
                            "codeStr": "Sound",
                            "stringArgs": [
                                "SE/break_glass_crack_lab.ogg"
                            ],
                            "intArgs": [
                                33554464,
                                0,
                                0,
                                0,
                                100,
                                100
                            ],
                            "index": 0
                        }
                    ]
                }
            ]
        },
        {
            "id": 7,
            "name": "人形起動",
            "pages": [
                {
                    "id": 0,
                    "list": [
                        {
                            "code": 124,
                            "codeStr": "SetVariableEx",
                            "intArgs": [
                                1100000,
                                4096,
                                4294967294,
                                1
                            ],
                            "index": 0
                        },
                        {
                            "code": 111,
                            "codeStr": "VariableCondition",
                            "intArgs": [
                                2,
                                1100000,
                                10,
                                3,
                                1100000,
                                11,
                                1
                            ],
                            "index": 1
                        },
                        {
                            "code": 401,
                            "codeStr": "ChoiceCase",
                            "intArgs": [
                                1
                            ],
                            "index": 2
                        },
                        {
                            "code": 111,
                            "codeStr": "VariableCondition",
                            "intArgs": [
                                1,
                                1100008,
                                0,
                                2
                            ],
                            "index": 3
                        },
                        {
                            "code": 401,
                            "codeStr": "ChoiceCase",
                            "intArgs": [
                                1
                            ],
                            "index": 4
                        },
                        {
                            "code": 130,
                            "codeStr": "Teleport",
                            "intArgs": [
                                3,
                                23,
                                19,
                                0,
                                0
                            ],
                            "index": 5
                        },
                        {
                            "code": 121,
                            "codeStr": "SetVariable",
                            "intArgs": [
                                1100008,
                                1,
                                0,
                                0
                            ],
                            "index": 6
                        },
                        {
                            "code": 150,
                            "codeStr": "Picture",
                            "intArgs": [
                                2,
                                3000,
                                0
                            ],
                            "index": 9
                        },
                        {
                            "code": 121,
                            "codeStr": "SetVariable",
                            "intArgs": [
                                1000031,
                                1,
                                0,
                                0
                            ],
                            "index": 10
                        },
                        {
                            "code": 401,
                            "codeStr": "ChoiceCase",
                            "intArgs": [
                                2
                            ],
                            "index": 12
                        },
                        {
                            "code": 121,
                            "codeStr": "SetVariable",
                            "intArgs": [
                                1000031,
                                0,
                                0,
                                0
                            ],
                            "index": 13
                        },
                        {
                            "code": 121,
                            "codeStr": "SetVariable",
                            "intArgs": [
                                1100008,
                                0,
                                0,
                                0
                            ],
                            "index": 14
                        },
                        {
                            "code": 111,
                            "codeStr": "VariableCondition",
                            "intArgs": [
                                2,
                                1100000,
                                18,
                                3,
                                1100000,
                                19,
                                1
                            ],
                            "index": 17
                        },
                        {
                            "code": 401,
                            "codeStr": "ChoiceCase",
                            "intArgs": [
                                1
                            ],
                            "index": 18
                        },
                        {
                            "code": 111,
                            "codeStr": "VariableCondition",
                            "intArgs": [
                                1,
                                1100009,
                                0,
                                2
                            ],
                            "index": 19
                        },
                        {
                            "code": 401,
                            "codeStr": "ChoiceCase",
                            "intArgs": [
                                1
                            ],
                            "index": 20
                        },
                        {
                            "code": 130,
                            "codeStr": "Teleport",
                            "intArgs": [
                                4,
                                17,
                                8,
                                0,
                                0
                            ],
                            "index": 21
                        },
                        {
                            "code": 121,
                            "codeStr": "SetVariable",
                            "intArgs": [
                                1100009,
                                1,
                                0,
                                0
                            ],
                            "index": 22
                        },
                        {
                            "code": 121,
                            "codeStr": "SetVariable",
                            "intArgs": [
                                1000041,
                                1,
                                0,
                                0
                            ],
                            "index": 25
                        },
                        {
                            "code": 401,
                            "codeStr": "ChoiceCase",
                            "intArgs": [
                                2
                            ],
                            "index": 27
                        },
                        {
                            "code": 121,
                            "codeStr": "SetVariable",
                            "intArgs": [
                                1000041,
                                0,
                                0,
                                0
                            ],
                            "index": 28
                        },
                        {
                            "code": 121,
                            "codeStr": "SetVariable",
                            "intArgs": [
                                1100009,
                                0,
                                0,
                                0
                            ],
                            "index": 29
                        },
                        {
                            "code": 150,
                            "codeStr": "Picture",
                            "intArgs": [
                                2,
                                3001,
                                0
                            ],
                            "index": 30
                        }
                    ]
                }
            ]
        },
        {
            "id": 8,
            "name": "窓の光",
            "pages": [
                {
                    "id": 0,
                    "list": []
                }
            ]
        },
        {
            "id": 9,
            "name": "窓の光",
            "pages": [
                {
                    "id": 0,
                    "list": []
                }
            ]
        },
        {
            "id": 10,
            "name": "窓の光",
            "pages": [
                {
                    "id": 0,
                    "list": []
                }
            ]
        },
        {
            "id": 11,
            "name": "窓の光",
            "pages": [
                {
                    "id": 0,
                    "list": []
                }
            ]
        },
        {
            "id": 12,
            "name": "窓の光",
            "pages": [
                {
                    "id": 0,
                    "list": []
                }
            ]
        },
        {
            "id": 13,
            "name": "窓の光",
            "pages": [
                {
                    "id": 0,
                    "list": []
                }
            ]
        },
        {
            "id": 14,
            "name": "場所移動",
            "pages": [
                {
                    "id": 0,
                    "list": [
                        {
                            "code": 300,
                            "codeStr": "CommonEventByName",
                            "stringArgs": [
                                "かくれんぼ"
                            ],
                            "intArgs": [
                                0,
                                20,
                                4294967295,
                                0,
                                13,
                                22,
                                3000000
                            ],
                            "index": 0
                        }
                    ]
                }
            ]
        },
        {
            "id": 15,
            "name": "場所移動",
            "pages": [
                {
                    "id": 0,
                    "list": [
                        {
                            "code": 300,
                            "codeStr": "CommonEventByName",
                            "stringArgs": [
                                "かくれんぼ"
                            ],
                            "intArgs": [
                                0,
                                20,
                                4294967295,
                                0,
                                27,
                                14,
                                3000000
                            ],
                            "index": 0
                        }
                    ]
                }
            ]
        },
        {
            "id": 16,
            "name": "場所移動",
            "pages": [
                {
                    "id": 0,
                    "list": [
                        {
                            "code": 300,
                            "codeStr": "CommonEventByName",
                            "stringArgs": [
                                "かくれんぼ"
                            ],
                            "intArgs": [
                                0,
                                20,
                                4294967295,
                                0,
                                14,
                                8,
                                3000000
                            ],
                            "index": 0
                        }
                    ]
                }
            ]
        }
    ]
}