{
    "id": 154,
    "name": "チェックポイント",
    "description": "",
    "commands": [
        {
            "code": 121,
            "codeStr": "SetVariable",
            "intArgs": [
                1600010,
                20010,
                0,
                0
            ],
            "index": 0
        },
        {
            "code": 121,
            "codeStr": "SetVariable",
            "intArgs": [
                1600010,
                1600001,
                0,
                256
            ],
            "index": 1
        },
        {
            "code": 111,
            "codeStr": "VariableCondition",
            "intArgs": [
                17,
                1600000,
                4294967295,
                2
            ],
            "index": 2
        },
        {
            "code": 401,
            "codeStr": "ChoiceCase",
            "intArgs": [
                1
            ],
            "index": 3
        },
        {
            "code": 124,
            "codeStr": "SetVariableEx",
            "intArgs": [
                1600011,
                4096,
                4294967295,
                6
            ],
            "index": 4
        },
        {
            "code": 124,
            "codeStr": "SetVariableEx",
            "intArgs": [
                1600012,
                4096,
                4294967295,
                7
            ],
            "index": 5
        },
        {
            "code": 420,
            "codeStr": "ElseCase",
            "intArgs": [
                0
            ],
            "index": 7
        },
        {
            "code": 124,
            "codeStr": "SetVariableEx",
            "intArgs": [
                1600011,
                4096,
                1600000,
                6
            ],
            "index": 8
        },
        {
            "code": 124,
            "codeStr": "SetVariableEx",
            "intArgs": [
                1600012,
                4096,
                1600000,
                7
            ],
            "index": 9
        },
        {
            "code": 121,
            "codeStr": "SetVariable",
            "intArgs": [
                1600012,
                1600002,
                0,
                256
            ],
            "index": 12
        },
        {
            "code": 150,
            "codeStr": "Picture",
            "stringArgs": [
                "SystemFile/icon.png"
            ],
            "intArgs": [
                33558528,
                1600010,
                0,
                10,
                10,
                7,
                255,
                1600011,
                1600012,
                200,
                0
            ],
            "index": 13
        },
        {
            "code": 290,
            "codeStr": "Effect",
            "intArgs": [
                160,
                10,
                1600010,
                1600010,
                7,
                9,
                0
            ],
            "index": 14
        }
    ]
}